starlette_static_cache_control/__init__.py
starlette_static_cache_control/class_.py
starlette_static_cache_control-1.0.0.dist-info/METADATA
starlette_static_cache_control-1.0.0.dist-info/WHEEL
starlette_static_cache_control-1.0.0.dist-info/RECORD
